src/test.py
edible-0.0.1.dist-info/LICENSE.txt
edible-0.0.1.dist-info/METADATA
edible-0.0.1.dist-info/WHEEL
edible-0.0.1.dist-info/top_level.txt
edible-0.0.1.dist-info/RECORD
