Metadata-Version: 2.1
Name: edible
Version: 0.0.1
Summary: A small example package
Home-page: https://github.com/thartvigsen/grace
Author: Thomas Hartvigsen
Author-email: Tom Hartvigsen <tomh@mit.edu>
License: BSD 2-clause
Project-URL: Homepage, https://github.com/hartvigsen/editing
Project-URL: Bug Tracker, https://github.com/pypa/editing/issues
Classifier: Programming Language :: Python :: 3
Classifier: License :: OSI Approved :: MIT License
Classifier: Operating System :: OS Independent
Requires-Python: >=3.7
License-File: LICENSE.txt
Requires-Dist: torch
Requires-Dist: numpy
Requires-Dist: transformers ==4.16.2
Requires-Dist: pandas
